churchrepl/__init__.py
churchrepl/__main__.py
churchrepl/repl/__init__.py
churchrepl/repl/lexer.py
churchrepl/repl/parser.py
churchrepl-1.0.2.dist-info/DESCRIPTION.rst
churchrepl-1.0.2.dist-info/METADATA
churchrepl-1.0.2.dist-info/RECORD
churchrepl-1.0.2.dist-info/WHEEL
churchrepl-1.0.2.dist-info/entry_points.txt
churchrepl-1.0.2.dist-info/metadata.json
churchrepl-1.0.2.dist-info/top_level.txt
