Metadata-Version: 2.0
Name: churchrepl
Version: 1.0.2
Summary: A simple REPL for lambda calculus
Home-page: https://github.com/CodeGrimoire/ChurchREPL
Author: Luke Smith
Author-email: lsmith@zenoscave.com
License: BSD
Platform: UNKNOWN
Classifier: Development Status :: 4 - Beta
Classifier: License :: OSI Approved :: BSD License
Classifier: Programming Language :: Python :: 2.7
Classifier: Programming Language :: Python :: 3
Classifier: Programming Language :: Python :: 3.4
Classifier: Operating System :: MacOS :: MacOS X
Classifier: Operating System :: POSIX :: Linux
Classifier: Operating System :: Microsoft :: Windows :: Windows 7
Requires-Dist: coverage
Requires-Dist: flake8
Requires-Dist: future
Requires-Dist: grako
Requires-Dist: mock
Requires-Dist: nose
Requires-Dist: pylint
